dfds_ds_toolbox/__init__.py
dfds_ds_toolbox/analysis/__init__.py
dfds_ds_toolbox/analysis/plotting.py
dfds_ds_toolbox/analysis/plotting_utils.py
dfds_ds_toolbox/exeptions.py
dfds_ds_toolbox/feature_extraction/__init__.py
dfds_ds_toolbox/feature_selection/__init__.py
dfds_ds_toolbox/logging/__init__.py
dfds_ds_toolbox/logging/logging.py
dfds_ds_toolbox/model_selection/__init__.py
dfds_ds_toolbox/model_selection/model_selection.py
dfds_ds_toolbox/profiling/__init__.py
dfds_ds_toolbox/profiling/profiling.py
dfds_ds_toolbox-0.11.0.dist-info/LICENSE
dfds_ds_toolbox-0.11.0.dist-info/METADATA
dfds_ds_toolbox-0.11.0.dist-info/WHEEL
dfds_ds_toolbox-0.11.0.dist-info/RECORD
